<root main_tree_to_execute="MainTree">
  <BehaviorTree ID="MainTree">
    <RecoveryNode number_of_retries="255" name="NavigateRecovery">
      <PipelineSequence name="NavigateWithReplanning">
        <RateController hz="1.0">
          <ReactiveFallback name="FollowInZoneOrNavigate">
            <Sequence name="FollowBranch">
              <IsInFollowZone goal="{goal}" radius="5" robot_frame="base_link"/>
              <AcquireFrontTarget goal="{goal}" objects_topic="/detected_objects" max_offset_deg="25.0" max_range="3.0" target="{target}"/>
              <GoalUpdater input_goal="{target}" output_goal="{updated_goal}">
                <ComputePathToPose goal="{updated_goal}" path="{path}" planner_id="GridBased"/>
              </GoalUpdater>
              <TruncatePath distance="1.0" input_path="{path}" output_path="{path}"/>
            </Sequence>
            <ComputePathToPose goal="{goal}" path="{path}" planner_id="GridBased"/>
          </ReactiveFallback>
        </RateController>
        <RecoveryNode number_of_retries="10" name="FollowPath">
          <FollowPath path="{path}" controller_id="FollowPath"/>
          <ClearEntireCostmap name="ClearLocalCostmap-Context" service_name="local_costmap/clear_entirely_local_costmap"/>
        </RecoveryNode>
      </PipelineSequence>
      <ReactiveFallback name="RecoveryFallback">
        <GoalUpdated/>
        <RoundRobin name="RecoveryActions">
          <Sequence name="ClearingActions">
            <ClearEntireCostmap name="ClearLocalCostmap-Subtree" service_name="local_costmap/clear_entirely_local_costmap"/>
            <ClearEntireCostmap name="ClearGlobalCostmap-Subtree" service_name="global_costmap/clear_entirely_global_costmap"/>
          </Sequence>
          <Wait wait_duration="5"/>
        </RoundRobin>
      </ReactiveFallback>
    </RecoveryNode>
  </BehaviorTree>
</root>
